[
    {
        "park_name": "อุทยานแห่งชาติขุนขาน",
        "park_phone": "0 5200 0410",
        "park_location": "หมู่ 1 ต.แม่สาบ อ.สะเมิง จ.เชียงใหม่ 50250",
        "park_email": "Khunkhan_np@hotmail.com",
        "park_activity": "ทางเดินศึกษาธรรมชาติ, เที่ยวถ้ำ/ศึกษาสภาพธรณี, ชมพรรณไม้, ดูนก/ดูผีเสื้อ, ดูดาว, ตั้งแคมป์พักแรม",
        "park_biome": "ป่าดิบเขา, ป่าดิบแล้ง, ป่าสนเขา, ป่าเบญจพรรณ, ป่าเต็งรัง",
        "park_animal": "เก้ง, หมูป่า, ไก่ป่า, เม่น, หมาไน, หมาจิ้งจอก, นิ่ม, ตุ่น, กระรอก, กระต่ายป่า, บ่าง, ค้างคาว, อีเห็น, พังพอน, ลิง, ชะนี, เสือ, เลียงผา, นกกก",
        "park_fee": "ชาวไทย: ผู้ใหญ่ 20 บาท เด็ก 10 บาท, ชาวต่างชาติ: ผู้ใหญ่ 100 บาท เด็ก 50 บาท"
    },
    {
        "park_name": "อุทยานแห่งชาติดอยผ้าห่มปก",
        "park_phone": "0 5208 0801, 084 483 4689",
        "park_location": "224 ม.6 ต.โป่งน้ำร้อน อ.ฝาง จ.เชียงใหม่ 50110",
        "park_email": "doiphahompok.np@hotmail.com",
        "park_activity": "ทางเดินศึกษาธรรมชาติ , เที่ยวน้ำตก , เที่ยวถ้ำ/ศึกษาสภาพธรณี , ชมพรรณไม้ , ดูนก/ดูผีเสื้อ , ดูดาว , อาบน้ำแร่/อบไอน้ำ , ตั้งแคมป์พักแรม",
        "park_biome": "ป่าเต็งรัง, ป่าเบญจพรรณ, ป่าดิบแล้ง, ป่าสนเขา, ป่าดิบเขา",
        "park_animal": "หมาไม้, หมีควาย, เก้ง, หมูป่า, เม่นใหญ่, กระต่ายป่า, ลิงกัง, ค่างแว่นถิ่นเหนือ, กระรอกท้องแดง, กระรอกดินแก้มแดง, กระรอกบินจิ๋วท้องขาว, เพียงพอนเส้นหลังขาว, เพียงพอนท้องเหลือง, นกติ๊ดหัวแดง, นกขัติยา, นกกระรางอกลาย, นกหัวขวานอกแดง, นกเดินดงสีน้ำตาลแดง, นกเดินดงอกเทา, นกเดินดงสีคล้ำ, นกเดินดงลายเสือ, กิ้งก่าแก้ว, เต่าปูลู, เต่าหก, งูลายสาบคอแดง, งูทางมะพร้าวแดง, งูสามเหลี่ยม, ตะกวด, กบดอยผ้าห่มปก, อึ่งอ่างบ้าน, กบหนอง, อึ่งแม่หนาว, อึ่งกรายห้วยเล็ก, ปาดตีนเหลืองเหนือ, กระท่าง",
        "park_fee": "ชาวไทย: ผู้ใหญ่ 60 บาท เด็ก 30 บาท, ชาวต่างชาติ: ผู้ใหญ่ 300 บาท เด็ก 150 บาท"
    },
    {
        "park_name": "อุทยานแห่งชาติดอยเวียงผา",
        "park_phone": "087 186 2118, 0 5331 7535",
        "park_location": "หมู่ที่ 8 ต.ศรีดงเย็น อ.ไชยปราการ จ.เชียงใหม่",
        "park_email": "doiwiangpha@hotmail.com",
        "park_activity": "ทางเดินศึกษาธรรมชาติ, ทางเดินป่า, เที่ยวน้ำตก, เที่ยวน้ำตก, ชมพรรณไม้, ดูนก/ดูผีเสื้อ",
        "park_biome": "ป่าเบญจพรรณ, ป่าเต็งรัง, ป่าดิบเขา, ป่าดิบแล้ง, ป่าสนเขา",
        "park_animal": "เก้ง, หมูป่า, เลียงผา, เสือไฟ, หมีควาย, เม่น, กระต่ายป่า, ลิง, อีเห็น, กระรอก, กระแต, นก",
        "park_fee": "ไม่เก็บค่าบริการ"
    },
    {
        "park_name": "อุทยานแห่งชาติดอยสุเทพ-ปุย",
        "park_phone": "0 5321 0244",
        "park_location": "ถนนศรีวิชัย ตำบลสุเทพ อำเภอเมือง จังหวัดเชียงใหม่ 50200",
        "park_email": "doisutheppui@gmail.com",
        "park_activity": "ทางเดินศึกษาธรรมชาติ, เที่ยวน้ำตก, ชมพรรณไม้, ดูนก/ดูผีเสื้อ, ส่องสัตว์, จักรยาน/จักรยานเสือภูเขา, ตั้งแคมป์พักแรม",
        "park_biome": "ป่าเต็งรัง, ป่าเบญจพรรณ, ป่าดิบแล้ง, ป่าดิบเขา",
        "park_animal": "หมูป่า, อีเห็นเครือ, อีเห็นข้างลาย, เม่นหางพวง, อ้นเล็ก, กระจ้อน, กระเล็นขนปลายหูสั้น, ค้างคาวมงกุฎเล็ก, หนูขนเสี้ยนดอย, หนูท้องขาว, เต่าปูลู, จิ้งจกบ้านหางแบนเล็ก, กิ้งก่าหัวแดง, งูสายม่านพระอินทร์, งูแส้หางม้าเทา, อึ่งกรายหัวเล็ก, กบหนอง, อึ่งขาคำ",
        "park_fee": "ชาวไทย: ผู้ใหญ่ 20 บาท เด็ก 10 บาท, ชาวต่างชาติ: ผู้ใหญ่ 100 บาท เด็ก 50 บาท"
    },
    {
        "park_name": "อุทยานแห่งชาติดอยอินทนนท์",
        "park_phone": "0 5328 6729",
        "park_location": "119 หมู่7 ต.บ้านหลวง อ.จอมทอง จ.เชียงใหม่ 50160",
        "park_email": "inthanon98dnp@hotmail.com",
        "park_activity": "ทางเดินศึกษาธรรมชาติ , เที่ยวน้ำตก , ชมพรรณไม้ , ดูนก/ดูผีเสื้อ , ส่องสัตว์ , ดูดาว , จักรยาน/จักรยานเสือภูเขา , ชมประวัติศาสตร์/วัฒนธรรม , ตั้งแคมป์พักแรม",
        "park_biome": "ป่าเต็งรัง, ป่าเบญจพรรณ, ป่าดิบแล้ง, ป่าดิบเขาตอนล่าง, ป่าดิบเขาตอนบน",
        "park_animal": "กระรอก, กระแตธรรมดา, กระเล็นขนปลายหูสั้น, อ้นเล็ก, เม่นหางพวง, อีเห็นข้างลาย, ชะมดแผงสันหางดำ, นกแซงแซวเล็กเหลือบ, นกปรอดหัวสีเขม่า, นกเด้าดินทุ่ง, เหยี่ยว, ไก่ฟ้าหลังขาว, นกเงือกคอแดง, นกพญาไฟสีกุหลาบ, กิ้งก่าหัวสีฟ้า, จิ้งเหลนเรียวจุดดำ, ตุ๊กแกบ้าน, งูลายสอคอแดง, กบห้วยสีข้างดำ, เขียดหนอง, อึ่งกราย, คางคกเล็ก, ปาดแคระ, หนูหญ้าดอย, กระท่าง, เต่าปูลู, นกศิวะหางสีน้ำตาล, นกปีกสั้นสีนำเงิน, นกกระจิ๊ดคอสีเทา, นกกินปลีหางยาว",
        "park_fee": "ชาวไทย: ผู้ใหญ่ 60 บาท เด็ก 30 บาท, ชาวต่างชาติ: ผู้ใหญ่ 300 บาท เด็ก 150 บาท"
    },
    {
        "park_name": "อุทยานแห่งชาติน้ำตกบัวตอง - น้ำพุเจ็ดสี",
        "park_phone": "093 193 3556",
        "park_location": "หมู่ที่ 8 ต.แม่หอพระ อ.แม่แตง จ.เชียงใหม่",
        "park_email": "namtokbuatong@gmail.com",
        "park_activity": "ทางเดินศึกษาธรรมชาติ, ทางเดินป่า, เที่ยวน้ำตก, ดูนก/ดูผีเสื้อ",
        "park_biome": "ป่าดิบชื้น, ป่าเบญจพรรณ, ป่าเต็งรัง",
        "park_animal": "นก, เก้ง, หมูป่า, ลิง, อีเห็น, หมาใน, หมูหริ่ง, แมวป่า, เม่น, พังพอน, กระต่ายป่า, กระรอก, กระรอกบิน, กระแต, ค้างคาว, เต่าใบไม้, ตะพาบน้ำ, กบ, กบจุก, เขียดแล้ว, อึ่งอ่าง, คางคก, ปูจั่ว, ปูเหล็ก, งูเหลือม, งูหลาม, งูจงอาง, งูเห่า, งูกระปะ(งูเปา), งูสามเหลี่ยม, งูเขียวหางไหม้, ลิ่น, ตุ๊กแก, กิ้งก่า, จิ้งเหลน, ตะกวด, ปลาช่อน, ปลาดุก, ปลากั้ง, ปลาซิว, ปลาปกขาว, ปลาหลอดหรือปลามัน, ปลาปั่น, ปลาขี้สุ่น, ปลากระทิง, ปลาหลด, ปลาน้ำหมึก, ปลาเข็ม, ปลาไหล, ปลาหมอ",
        "park_fee": "ไม่เก็บค่าบริการ"
    },
    {
        "park_name": "อุทยานแห่งชาติผาแดง",
        "park_phone": "0 5304 6370",
        "park_location": "หมู่ 3 บ้านนาหวาย ตำบลเมืองนะ อำเภอเชียงดาว จังหวัดเชียงใหม่ 50170",
        "park_email": "np.phadaeng@hotmail.com",
        "park_activity": "ทางเดินศึกษาธรรมชาติ, เที่ยวน้ำตก, ชมพรรณไม้, ดูนก/ดูผีเสื้อ, ตั้งแคมป์พักแรม",
        "park_biome": "ป่าเบญจพรรณ, ป่าเต็งรัง, ป่าดิบเขา, ป่าสนเขา",
        "park_animal": "กวางผา, เลียงผา, เก้ง, หมู่ป่า, เม่น, หมี, ค่าง, อีเห็น, นางอาย (ลิงลม), กระรอก, เต่าปูรู, เขียดแหลว",
        "park_fee": "ชาวไทย: ผู้ใหญ่ 20 บาท เด็ก 10 บาท, ชาวต่างชาติ: ผู้ใหญ่ 100 บาท เด็ก 50 บาท"
    },
    {
        "park_name": "อุทยานแห่งชาติแม่ตะไคร้",
        "park_phone": "0 5200 0832 , 09 5694 5052",
        "park_location": "อุทยานแห่งชาติแม่ตะไคร้\t36 หมู่ 3 บ้านแม่หวาน ต.ป่าเมี่ยง อ.ดอยสะเก็ด จ.เชียงใหม่ 50220",
        "park_email": "sarbanmaetakhrai@dnp.mail.go.th",
        "park_activity": "ชมพรรณไม้, ดูนก/ดูผีเสื้อ, ดูดาว, ตั้งแคมป์พักแรม",
        "park_biome": "ป่าเบญจพรรณ, ป่าดิบแล้ง, ป่าเต็งรัง, ป่าสนเขา, ป่าดิบเขา",
        "park_animal": "เก้ง, กวางป่า, กระต่ายป่า, ลิง, ชะนี, ชะมด, เม่น, อีเห็น, เสือโคร่ง, หมูป่า, เลียงผา, หมี, นกกางเขนดง, นกแซงแซวหางม่วง, นกหัวขวาน, นกยูง, นกขุนทอง, นกยาง, ไก่ป่า, นกเค้าแมว, นกกระปูด, กิ้งก่าชนิดต่างๆ, งูชนิดต่างๆ, เต่า, กบ, อึ่ง, ปาด, ผีเสื้อหางดาบตาลไหม้, ด้วงคีมยีราฟ",
        "park_fee": "ชาวไทย: ผู้ใหญ่ 20 บาท เด็ก 10 บาท, ชาวต่างชาติ: ผู้ใหญ่ 100 บาท เด็ก 50 บาท"
    },
    {
        "park_name": "อุทยานแห่งชาติแม่โถ",
        "park_phone": "089 526 0116",
        "park_location": "อุทยานแห่งชาติแม่โถ ตู้ ปณ.10 ปณจ.ฮอด อ.ฮอด จ.เชียงใหม่ 50240",
        "park_email": "maetho41@gmail.com",
        "park_activity": "ทางเดินศึกษาธรรมชาติ, ชมพรรณไม้, เที่ยวน้ำตก, ดูนก/ดูผีเสื้อ, ดูดาว, ล่องแก่ง, ตั้งแคมป์พักแรม",
        "park_biome": "ป่าดิบชื้น, ป่าดิบเขา, ป่าเบญจพรรณ, ป่าสนเขา",
        "park_animal": "กระทิง, กวางป่า, เลียงผา, เก้ง, หมีควาย, ชะนี, ลิง, ค่าง, อีเห็น, กระต่ายป่า, หมูป่า, ช้างป่า, นกยูง, ไก่ฟ้า, ไก่ป่า, นกแก้ว, นกขุนทอง, นกขุนแผน, เหยี่ยว, งูเหลือม, งูหลาม, งูเห่า, ตะกวด, แย้, เต่า, ตะพาบน้ำ, กบ, เขียด, อึ่งอ่าง",
        "park_fee": "ไม่เก็บค่าบริการ"
    },
    {
        "park_name": "อุทยานแห่งชาติแม่วาง",
        "park_phone": "053 106 759",
        "park_location": "ต.สันติสุข อำเภอดอยหล่อ จ.เชียงใหม่",
        "park_email": "maewang.np112@gmail.com",
        "park_activity": "ทางเดินศึกษาธรรมชาติ,เที่ยวถ้ำ/ศึกษาสภาพธรณี,ดูนก/ดูผีเสื้อ,ดูดาว,ตั้งแคมป์พักแรม",
        "park_biome": "ป่าเบญจพรรณ, ป่าเต็งรัง, ป่าสนเขา, ป่าดิบเขา",
        "park_animal": "เก้ง, หมูป่า, เสือปลา, ลิงวอก, ชะนีมือขาว, ชะมดเช็ด, หมาไม้, เม่นหางพวง, ลิ่นชวา, กระต่ายป่า, กระรอกท้องแดง, ค้างคาวดอย, เหยี่ยวรุ้ง, นกกระทาทุ่ง, ไก่ป่า, ไก่ฟ้าหางลายขวาง, นกคุ่มอกลาย, นกเขาเขียว, นกบั้งรอกใหญ่, นกเค้าโมง, นกแอ่นตาล, นกขุนแผนหัวแดง, นกแก๊ก, นกโพระดก, นกหัวขวานด่างแคระ, นกปรอดทอง, นกแซงแซวหางปลา, นกกินปลีหางยาวคอสีฟ้า, เต่าปูลู, เต่าเหลือง, กิ้งก่าบินปีกแดง, แย้, ตะกวด, งูเหลือม, งูสามเหลี่ยม, งูจงอาง, อึ่งลาย, กบห้วย, ปาดบ้าน, คางคกบ้าน",
        "park_fee": "ชาวไทย: ผู้ใหญ่ 20 บาท เด็ก 10 บาท, ชาวต่างชาติ: ผู้ใหญ่ 100 บาท เด็ก 50 บาท"
    },
    {
        "park_name": "อุทยานแห่งชาติศรีลานนา",
        "park_phone": "0 5347 9079, 0 5331 7495, 0 5347 9090",
        "park_location": "ต.บ้านเป้า อ.แม่แตง จ.เชียงใหม่ 50150",
        "park_email": "npsrilanna2566@gmail.com",
        "park_activity": "ทางเดินศึกษาธรรมชาติ, เที่ยวน้ำตก, ตั้งแคมป์พักแรม",
        "park_biome": "ป่าเต็งรัง, ป่าเบญจพรรณ, ป่าดิบแล้ง, ป่าสนเขา, ป่าดิบเขา",
        "park_animal": "เก้ง, อ้นกลาง, เม่นหางพวง, หมาไน, ชะมดเช็ด, อีเห็นเครือ, แมวป่า, กระต่ายป่า, กระรอกหลากสี, หนูท้องขาว, ค้างคาวขอบหูขาวกลาง, ค้างคาวหน้ายาวใหญ่, นกกะลิงเขียด, นกกาแวน, อีกา, นกจับแมลงจุกดำ, นกขมิ้นน้อยธรรมดา, นกนิลตวาท้องสีส้ม, นกกางเขนดง, นกยอดหญ้าหัวดำ, นกกระจิบธรรมดา, นกกระจิ๊ดเขียวปีกสองแถบ, นกกินแมลงป่าอกสีน้ำตาล, งูทางมะพร้าวลายขีด, งูสิงบ้าน, จิ้งจกดินจุดลาย, ตุ๊กแกบ้าน, กิ้งก่าบินคอสีส้ม, กบบัว, เขียดจะนา, อึ่งอ่างบ้าน, อี่งแม่หนาว, คางคกบ้าน, ปาดแคระป่า, นกกะเต็นน้อยธรรมดา, นกเป็ดแดง, กบนา, กบหนอง, อึ่งอี๊ดข้างขีด, ปลาจาด, ปลาแม่แปป, ปลาซิวหนวดยาว, ปลาเวียน, ปลาเข็ม, ปลาบู่, ปลาสร้อยขาว",
        "park_fee": "ชาวไทย: ผู้ใหญ่ 20 บาท เด็ก 10 บาท, ชาวต่างชาติ: ผู้ใหญ่ 100 บาท เด็ก 50 บาท"
    },
    {
        "park_name": "อุทยานแห่งชาติห้วยน้ำดัง (Huai Nam Dang)",
        "park_phone": "082 187 7834, 084 908 1531, 093 632 1601",
        "park_location": "อุทยานแห่งชาติห้วยน้ำดัง หมู่ 5 ต.กึ๊ดช้าง อ.แม่แตง จ.เชียงใหม่ 50150",
        "park_email": "namdangnp@hotmail.co.th",
        "park_activity": "ทางเดินศึกษาธรรมชาติ, เที่ยวน้ำตก, ชมพรรณไม้, ดูนก/ดูผีเสื้อ, ดูดาว, อาบน้ำแร่/อบไอน้ำ, ตั้งแคมป์พักแรม",
        "park_biome": "ป่าดิบชื้น, ป่าดิบเขา, ป่าเบญจพรรณ, ป่าเต็งรัง",
        "park_animal": "ช้างป่า, กวางป่า, หมีควาย, เก้ง, กระจงเล็ก, เลียงผา, หมูป่า, แมวดาว, ชะมดเช็ด, ลิงวอก, ชะนีมือขาว, พังพอน, เม่นใหญ่, ไก่ป่า, ไก่ฟ้าสีเงิน, นกเขาเปล้า, นกขุนทอง, นกขมิ้นท้ายทอยดำ, นกปรอดคอลาย, เหยี่ยวต่างสี, กะท่าง, เต่าปูลู, เต่าใบไม้, ก้งก่าแก้ว, แย้, ตะกวด, งูเหลือม, งูเขียวดอกหมาก, งูเห่า, กบทูด, ปาด, เขียดป่าไผ่, อึ่งลาย",
        "park_fee": "ชาวไทย: ผู้ใหญ่ 60 บาท เด็ก 30 บาท, ชาวต่างชาติ: ผู้ใหญ่ 150 บาท เด็ก 300 บาท"
    },
    {
        "park_name": "อุทยานแห่งชาติออบขาน",
        "park_phone": "08 6181 1068",
        "park_location": "อุทยานแห่งชาติออบขาน\tต.น้ำแพร่ อ.หางดง จ.เชียงใหม่ 50230",
        "park_email": "obkhanpark@gmail.com",
        "park_activity": "ทางเดินศึกษาธรรมชาติ, ทางเดินป่า, ชมประวัติศาสตร์/วัฒนธรรม, ชมพรรณไม้, ดูนก/ดูผีเสื้อ, ดูดาว, ตั้งแคมป์พักแรม",
        "park_biome": "ป่าเต็งรัง, ป่าเบญจพรรณ, ป่าดิบแล้ง, ป่าดิบเขา, ป่าสนเขา",
        "park_animal": "เลียงผา, เก้ง, หมีขอ, หมีควาย, เสือปลา, เสือไฟ, กระจง, อีเห็น, กระต่ายป่า, หมูป่า, ชะนี, ลิง, นางอาย, พังพอน, เม่น, หมาจิ้งจอก, กระรอก, กระแต, หนูต่างๆ, ตะพาบน้ำ, เต่าปูลู, ไก่ฟ้า",
        "park_fee": "ไม่เก็บค่าบริการ"
    },
    {
        "park_name": "อุทยานแห่งชาติออบหลวง",
        "park_phone": "081 602 1290",
        "park_location": "ตู้ ปณ.2 ต.หางดง อ.ฮอด จ.เชียงใหม่ 50240",
        "park_email": "opluang68@gmail.com",
        "park_activity": "ทางเดินศึกษาธรรมชาติ, ชมพรรณไม้, เที่ยวน้ำตก, ดูนก/ดูผีเสื้อ, อาบน้ำแร่/อบไอน้ำ, ชมประวัติศาสตร์/วัฒนธรรม,  ตั้งแคมป์พักแรม",
        "park_biome": "ป่าเต็งรัง, ป่าเบญจพรรณ, ป่าดิบแล้ง, ป่าดิบเขา, ป่าสนเขา",
        "park_animal": "อีเก้งธรรมดา, หมูป่า, ชะนี, ชะมด, กระต่ายป่า, นกกางเขนบ้าน, นกกางเขนดง, งู",
        "park_fee": "ชาวไทย: ผู้ใหญ่ 20 บาท เด็ก 10 บาท, ชาวต่างชาติ: ผู้ใหญ่ 100 บาท เด็ก 50 บาท"
    }
]